paddleocr_cli/__init__.py
paddleocr_cli/__main__.py
paddleocr_cli/mcp_server.py
fast_paddleocr_mcp-0.5.0.dist-info/METADATA
fast_paddleocr_mcp-0.5.0.dist-info/WHEEL
fast_paddleocr_mcp-0.5.0.dist-info/entry_points.txt
fast_paddleocr_mcp-0.5.0.dist-info/licenses/LICENSE
fast_paddleocr_mcp-0.5.0.dist-info/RECORD
